LICENCE.txt
MANIFEST.in
README.rst
setup.py
Gestus.egg-info/PKG-INFO
Gestus.egg-info/SOURCES.txt
Gestus.egg-info/dependency_links.txt
Gestus.egg-info/not-zip-safe
Gestus.egg-info/requires.txt
Gestus.egg-info/top_level.txt
gestus/__init__.py
gestus/admin.py
gestus/crumbs.py
gestus/models.py
gestus/urls.py
gestus/views.py
gestus/migrations/0001_initial.py
gestus/migrations/0002_auto__add_field_websiteenvironment_url.py
gestus/migrations/0003_fill_environment_url.py
gestus/migrations/0004_auto__del_field_website_url.py
gestus/migrations/0005_auto__add_field_egg_summary.py
gestus/migrations/__init__.py
gestus/rest/__init__.py
gestus/rest/serializers.py
gestus/rest/views.py
gestus/templates/gestus/base.html
gestus/templates/gestus/egg_detail.html
gestus/templates/gestus/egg_index.html
gestus/templates/gestus/environment_detail.html
gestus/templates/gestus/environment_index.html
gestus/templates/gestus/index.html
gestus/templates/gestus/server_detail.html
gestus/templates/gestus/server_index.html
gestus/templates/gestus/website_detail.html
gestus/templates/gestus/website_index.html