Metadata-Version: 1.1
Name: Gestus
Version: 0.3.4
Summary: Django application to manage some datas about Emencia client websites
Home-page: http://pypi.python.org/pypi/Gestus
Author: David Thenon
Author-email: dthenon@emencia.com
License: MIT
Platform: UNKNOWN
Classifier: Programming Language :: Python
Classifier: License :: OSI Approved :: MIT License
Classifier: Operating System :: OS Independent
Classifier: Development Status :: 3 - Alpha
Classifier: Environment :: Web Environment
Classifier: Framework :: Django
Classifier: Intended Audience :: Developers
Classifier: Topic :: Internet :: WWW/HTTP
Classifier: Topic :: Software Development :: Libraries :: Python Modules
